LICENSE
MANIFEST.in
README.md
package.json
setup.py
event_timeline/EventTimeline.py
event_timeline/__init__.py
event_timeline/_imports_.py
event_timeline/event_timeline.min.js
event_timeline/event_timeline.min.js.map
event_timeline/metadata.json
event_timeline/package-info.json
event_timeline.egg-info/PKG-INFO
event_timeline.egg-info/SOURCES.txt
event_timeline.egg-info/dependency_links.txt
event_timeline.egg-info/top_level.txt