Metadata-Version: 1.1
Name: event-timeline
Version: 0.0.1
Summary: event based timeline
Home-page: UNKNOWN
Author: kalimuthu periyasamy <1995kalimuthu@gmail.com>
Author-email: UNKNOWN
License: MIT
Platform: UNKNOWN
Classifier: Framework :: Dash
